AirDataUAV/__init__.py
AirDataUAV/air_data_uav_objects.py
AirDataUAV-0.0.6.dist-info/LICENSE
AirDataUAV-0.0.6.dist-info/METADATA
AirDataUAV-0.0.6.dist-info/WHEEL
AirDataUAV-0.0.6.dist-info/top_level.txt
AirDataUAV-0.0.6.dist-info/RECORD
