Metadata-Version: 2.1
Name: AirDataUAV
Version: 0.0.6
Summary: A nice interface to AirDataUAV CSV files
Home-page: https://github.com/iwishiwasaneagle/AirDataUAV
Author: Jan-Hendrik Ewers
Author-email: jh.ewers@gmail.com
License: UNKNOWN
Platform: UNKNOWN
Classifier: Programming Language :: Python :: 3 :: Only
Classifier: License :: OSI Approved :: GNU General Public License v3 (GPLv3)
Classifier: Operating System :: OS Independent
Requires-Python: >=3
